pygments_clingo/__init__.py
pygments_clingo/clingo.py
pygments_clingo-0.1.8.dist-info/LICENSE
pygments_clingo-0.1.8.dist-info/METADATA
pygments_clingo-0.1.8.dist-info/WHEEL
pygments_clingo-0.1.8.dist-info/entry_points.txt
pygments_clingo-0.1.8.dist-info/top_level.txt
pygments_clingo-0.1.8.dist-info/RECORD
