Metadata-Version: 2.1
Name: pygments-clingo
Version: 0.1.8
Summary: Syntax highlighting for clingo
Home-page: https://github.com/rkaminsk/pygments_clingo
Author: Roland Kaminski
Author-email: UNKNOWN
License: MIT
Platform: UNKNOWN
Requires-Dist: pygments
